{"cameraMode":{"drawMode":0,"name":"Shaded","section":"Shading Mode"},"sceneLighting":true,"audioPlay":false,"sceneViewState":{"m_AlwaysRefresh":false,"showFog":true,"showSkybox":true,"showFlares":true,"showImageEffects":true,"showParticleSystems":true,"showVisualEffectGraphs":true,"m_FxEnabled":true},"in2DMode":false,"pivot":{"x":0.07803106307983399,"y":0.9577469825744629,"z":-4.1678290367126469},"rotation":{"x":0.24163664877414704,"y":0.40978363156318667,"z":-0.11370142549276352,"w":0.8723046183586121},"size":3.706434965133667,"orthographic":false}